<?xml version="1.0" encoding="utf-8" ?>
<LanguageData>
	<CleanPathfinding.Settings.Header.Tuning>调整</CleanPathfinding.Settings.Header.Tuning>
	<CleanPathfinding.Settings.Header.Doorpathing>门</CleanPathfinding.Settings.Header.Doorpathing>
	<CleanPathfinding.Settings.Header.Rules>规则</CleanPathfinding.Settings.Header.Rules>
	<CleanPathfinding.Settings.Header.Misc>其他</CleanPathfinding.Settings.Header.Misc>

	<CleanPathfinding.Settings.Bias>污染地形规避（默认值：{0}，最小值：{1}，最大值：{2}）：</CleanPathfinding.Settings.Bias>
	<CleanPathfinding.Settings.Bias.Desc>对生成污染的地形格外增加路径成本。</CleanPathfinding.Settings.Bias.Desc>

	<CleanPathfinding.Settings.NaturalBias>岩块地形规避（默认值：{0}，最小值：{1}，最大值：{2}）：</CleanPathfinding.Settings.NaturalBias>
	<CleanPathfinding.Settings.NaturalBias.Desc>由于岩块地形不会生成污染，上述设置可能会导致角色过于倾向于走在上面，这取决于地图布局。可以调整此设置避免这种行为。</CleanPathfinding.Settings.NaturalBias.Desc>

	<CleanPathfinding.Settings.RoadBias>道路吸引（默认值：{0}，最小值：{1}，最大值：{2}）：</CleanPathfinding.Settings.RoadBias>
	<CleanPathfinding.Settings.RoadBias.Desc>对所有带有“道路”标记的地块减少预期路径成本。</CleanPathfinding.Settings.RoadBias.Desc>

	<CleanPathfinding.Settings.EnableRegionPathing>启用区域寻路</CleanPathfinding.Settings.EnableRegionPathing>
	<CleanPathfinding.Settings.EnableRegionPathing.Desc>启用后，</CleanPathfinding.Settings.EnableRegionPathing.Desc>
	<CleanPathfinding.Settings.RegionModeThreshold>区域寻路阈值 (默认值：{0}，最小值：{1}，最大值：{2})：</CleanPathfinding.Settings.RegionModeThreshold>
	<CleanPathfinding.Settings.RegionModeThreshold.Desc>如果一个角色的路径计算超过了此阈值，它们将切换到“区域寻路模式”，导致计算分块为12x12个块。这会更耗费性能，但可以扩大搜索范围，使其发现更好的路径，例如道路等。此选项适合那些致力于建立良好寻路基础设施的玩家。\n\n如果您降低此阈值，请考虑降低'并行扩散微调'，或将其完全关闭。</CleanPathfinding.Settings.RegionModeThreshold.Desc>

	<CleanPathfinding.Settings.EnableTuning>启用寻路调整</CleanPathfinding.Settings.EnableTuning>
	<CleanPathfinding.Settings.EnableTuning.Desc>关闭此选项将使寻路行为恢复到原版的普通寻路模式。</CleanPathfinding.Settings.EnableTuning.Desc>

	<CleanPathfinding.Settings.DarknessPenalty>黑暗惩罚（默认值：{0}，最小值：{1}，最大值：{2}）：</CleanPathfinding.Settings.DarknessPenalty>
	<CleanPathfinding.Settings.DarknessPenalty.Desc>在黑暗的格子添加额外的寻路成本。</CleanPathfinding.Settings.DarknessPenalty.Desc>

	<CleanPathfinding.Settings.FactorLight>路径规划应考虑光线</CleanPathfinding.Settings.FactorLight>
	<CleanPathfinding.Settings.FactorLight.Desc>角色将会考虑并倾向于选择更光亮的路径，这将产生额外的计算，并对性能造成轻微的影响。</CleanPathfinding.Settings.FactorLight.Desc>
	<CleanPathfinding.Settings.HeuristicAdjuster>'并行扩散微调'（默认值：{0}，最小值：{1}，最大值：{2}）：{3}</CleanPathfinding.Settings.HeuristicAdjuster>
	<CleanPathfinding.Settings.HeuristicAdjuster.Desc>基于目标的位置向更远的区域扩散搜索，较高的值会导致计算像基于目标的锥体一样膨胀。当达到最大值时，会分析大量单元格以获取最高的精度，但性能代价也很高。</CleanPathfinding.Settings.HeuristicAdjuster.Desc>

	<CleanPathfinding.Settings.FactorCarryingPawn>如果携带其他角色，角色将忽略规则</CleanPathfinding.Settings.FactorCarryingPawn>
	<CleanPathfinding.Settings.FactorCarryingPawn.Desc>如果角色正在携带另一名角色，它们将忽略规则。</CleanPathfinding.Settings.FactorCarryingPawn.Desc>

	<CleanPathfinding.Settings.FactorBleeding>流血时忽略规则</CleanPathfinding.Settings.FactorBleeding>
	<CleanPathfinding.Settings.FactorBleeding.Desc>如果角色每天流血量超过10%，则它们将忽略规则。</CleanPathfinding.Settings.FactorBleeding.Desc>

	<CleanPathfinding.Settings.EnableExitTuning>启用出口寻路</CleanPathfinding.Settings.EnableExitTuning>
	<CleanPathfinding.Settings.ExitRange.Warning>仅在你玩一张不寻常的地图，并发现角色正在寻找地图出口时被卡住时需要使用出口寻路功能。更改此功能需要重新启动游戏。</CleanPathfinding.Settings.ExitRange.Warning>
	<CleanPathfinding.Settings.ExitRange>出口寻路范围（默认值：{0}，最小值：{1}，最大值：{2}）：</CleanPathfinding.Settings.ExitRange>
	<CleanPathfinding.Settings.ExitRange.Desc>角色会四处寻找出口，每次寻找距离增加+4格。在原版中，它们在30次迭代后放弃。这个滑块增加了迭代次数，使它们的出口寻找更积极。</CleanPathfinding.Settings.ExitRange.Desc>

	<CleanPathfinding.Settings.EnableWanderTuning>启用闲逛调整</CleanPathfinding.Settings.EnableWanderTuning>
	<CleanPathfinding.Settings.EnableWanderTuning.Desc>允许对闲逛的角色和动物进行调整。</CleanPathfinding.Settings.EnableWanderTuning.Desc>
	<CleanPathfinding.Settings.WanderDelay>闲逛延迟时间（Mod默认：{0}，最小值：{1}，最大值：{2}）{3}</CleanPathfinding.Settings.WanderDelay>
	<CleanPathfinding.Settings.WanderDelay.Desc>增加下一次走动的额外秒数，使得角色（包括动物）在闲逛到一个新的附近地点之前等待一段时间。增加这个值可以在一定程度上提高性能，但代价是世界的生动程度降低。</CleanPathfinding.Settings.WanderDelay.Desc>

	<CleanPathfinding.Settings.DoorPathing>启用门路线</CleanPathfinding.Settings.DoorPathing>
	<CleanPathfinding.Settings.DoorPathing.Desc>允许为门添加标记，以设置路径优先级。</CleanPathfinding.Settings.DoorPathing.Desc>
	<CleanPathfinding.Settings.DoorPathing.Notice>（当前游戏无法禁用门路径。）</CleanPathfinding.Settings.DoorPathing.Notice>

	<CleanPathfinding.Settings.DoorPathingSide>侧门的路径花费（默认值：{0}，最小值：{1}，最大值：{2}）： </CleanPathfinding.Settings.DoorPathingSide>
	<CleanPathfinding.Settings.DoorPathingSide.Desc>当穿过标记为侧门的门时，角色将考虑这个额外的路径花费。默认情况下，普通门被视为+45的花费。</CleanPathfinding.Settings.DoorPathingSide.Desc>
	<CleanPathfinding.Settings.DoorPathingEmergency>紧急门的路径花费（默认值：{0}，最小值：{1}，最大值：{2}）： </CleanPathfinding.Settings.DoorPathingEmergency>
	<CleanPathfinding.Settings.DoorPathingEmergency.Desc>当穿过标记为紧急门的门时，角色将考虑这个额外的路径花费。默认情况下，普通门被视为+45的花费。</CleanPathfinding.Settings.DoorPathingEmergency.Desc>

	<CleanPathfinding.Settings.OptimizeCollider>优化碰撞检测</CleanPathfinding.Settings.OptimizeCollider>
	<CleanPathfinding.Settings.OptimizeCollider.Desc>用优化版本替换检查角色是否与其他角色碰撞的代码。没有逻辑变化。如果检测到其他模组需要修改此代码并且可能会发生冲突，则此优化将自动禁用。更改此选项需要重新启动游戏。</CleanPathfinding.Settings.OptimizeCollider.Desc>

	<CleanPathfinding.Icon.DoorType.Desc>用于改变门的类型以影响路径规划行为。\n\n殖民者角色通常会更倾向于选择正门，而不是侧门和紧急门。\n\n专用门适用于没有其他进入途径的房间，可以为路径规划提供提示。</CleanPathfinding.Icon.DoorType.Desc>
	<CleanPathfinding.Icon.Normal>正门</CleanPathfinding.Icon.Normal>
	<CleanPathfinding.Icon.Side>侧门</CleanPathfinding.Icon.Side>
	<CleanPathfinding.Icon.Emergency>紧急门</CleanPathfinding.Icon.Emergency>
	<CleanPathfinding.Icon.Exclusive>专用门</CleanPathfinding.Icon.Exclusive>

	<CleanPathfinding.InvalidDoor>房间只有一扇门时，无法设置门的优先级。</CleanPathfinding.InvalidDoor>

	<CleanPathfinding.ReloadHeader>需要重新加载</CleanPathfinding.ReloadHeader>
	<CleanPathfinding.ReloadRequired>重新加载存档以启用门路线功能。您不需要重新启动游戏。</CleanPathfinding.ReloadRequired>

	<CleanPathfinding.NewAvoidArea>[清理寻路路径] 注册了规避区域。</CleanPathfinding.NewAvoidArea>
	<CleanPathfinding.DeletedAvoidArea>[清理寻路路径] 删除了规避区域。</CleanPathfinding.DeletedAvoidArea>

	<Seconds>秒</Seconds>
	<Off><![CDATA[<color=green>OFF</color>]]></Off>
	<Max><![CDATA[<color=red>MAX</color>]]></Max>
</LanguageData>
